verilog_code/serial.v
`timescale 1ns/1ps
module serial_adder 
    (   input clk,reset, 
        input a,b,cin,  
        output reg s,cout  
        );

reg c,flag;

always@(posedge clk or posedge reset)
begin
    if(reset == 1) begin
        s = 0;
        cout = c;
        flag = 0;
    end else begin
        if(flag == 0) begin
            c = cin;  
            flag = 1;  
        end 
        cout = 0;
        s = a ^ b ^ c; 
        c = (a & b) | (c & b) | (a & c); 
    end 
end

endmodule 



// test bench


module tb;

reg clk;
reg reset;
reg a;
reg b;
reg cin;

wire s;
wire cout;

reg [8:0] sum_res;
reg [7:0] num1;
reg [7:0] num2;
integer i;

serial_adder uut (.*); // better to give mention proper connection depending on compiler.

always #5 clk = ~clk;

initial begin
    $dumpfile("serial_adder.vcd");
    $dumpvars(0, tb);

    clk = 1;
    reset = 1;
    sum_res = 0;
    a = 0;
    b = 0;
    cin = 0;

    #20 reset = 0;

    num1 = ($random & 8'hFF); // to avoid the negative number(& hFF)
    num2 = ($random & 8'hFF); 
    cin = 0;
    sum_res = 0;
    

    for (i = 0; i < 9; i = i + 1) begin
        a = (num1 >> i) & 1;
        b = (num2 >> i) & 1;
        #10 sum_res = sum_res | (s << i);
    end

    $display("number 1 = %d	number 2 = %d ",num1, num2);
    $display(" Final sum in decimal: %d", sum_res);

    #10 reset = 1;
    #10;
    $finish;
end

endmodule

verilog_code/serial_adder.vcd
$date
	Sat Mar 22 15:27:18 2025
$end
$version
	Icarus Verilog
$end
$timescale
	1ps
$end
$scope module tb $end
$var wire 1 ! s $end
$var wire 1 " cout $end
$var reg 1 # a $end
$var reg 1 $ b $end
$var reg 1 % cin $end
$var reg 1 & clk $end
$var reg 8 ' num1 [7:0] $end
$var reg 8 ( num2 [7:0] $end
$var reg 1 ) reset $end
$var reg 9 * sum_res [8:0] $end
$var integer 32 + i [31:0] $end
$scope module uut $end
$var wire 1 # a $end
$var wire 1 $ b $end
$var wire 1 % cin $end
$var wire 1 & clk $end
$var wire 1 ) reset $end
$var reg 1 , c $end
$var reg 1 " cout $end
$var reg 1 - flag $end
$var reg 1 ! s $end
$upscope $end
$upscope $end
$enddefinitions $end
$comment Show the parameter values. $end
$dumpall
$end
#0
$dumpvars
0-
x,
bx +
b0 *
1)
bx (
bx '
1&
0%
0$
0#
x"
0!
$end
#5000
0&
#10000
1&
#15000
0&
#20000
1!
0"
1-
0,
1&
1$
b0 +
b10000001 (
b100100 '
0)
#25000
0&
#30000
0!
1&
0$
b1 +
b1 *
#35000
0&
#40000
1!
1&
1#
b10 +
#45000
0&
#50000
0!
1&
0#
b11 +
b101 *
#55000
0&
#60000
1&
b100 +
#65000
0&
#70000
1!
1&
1#
b101 +
#75000
0&
#80000
0!
1&
0#
b110 +
b100101 *
#85000
0&
#90000
1!
1&
1$
b111 +
#95000
0&
#100000
0!
1&
0$
b1000 +
b10100101 *
#105000
0&
#110000
1&
b1001 +
#115000
0&
#120000
0-
1&
1)
